bsimport/__init__.py
bsimport/__main__.py
bsimport/cli.py
bsimport/config.py
bsimport/imp.py
bsimport/py.typed
bsimport/wrapper.py
bsimport-0.1.1.dist-info/LICENSE
bsimport-0.1.1.dist-info/METADATA
bsimport-0.1.1.dist-info/WHEEL
bsimport-0.1.1.dist-info/top_level.txt
bsimport-0.1.1.dist-info/RECORD
