Metadata-Version: 2.1
Name: bsimport
Version: 0.1.1
Summary: A tool for importing Markdown files to a Bookstack instance.
Home-page: https://github.com/JulioLoayzaM/bsimport
Author: JulioLoayzaM
License: MIT
Keywords: bookstack,import,markdown
Platform: any
Classifier: Development Status :: 7 - Inactive
Classifier: Intended Audience :: Developers
Classifier: License :: OSI Approved :: MIT License
Classifier: Operating System :: OS Independent
Classifier: Programming Language :: Python
Classifier: Programming Language :: Python :: 3
Classifier: Programming Language :: Python :: 3 :: Only
Requires-Python: >=3.6
License-File: LICENSE
Requires-Dist: requests (>=2.26.0)
Requires-Dist: typer (>=0.4.0)
Provides-Extra: testing
Requires-Dist: flake8 (>=4.0.1) ; extra == 'testing'
